{
  "indexes": [
    {
      "collectionGroup": "overbreaks",
      "queryScope": "COLLECTION",
      "fields": [
        {
          "fieldPath": "timestamp",
          "order": "DESCENDING"
        }
      ]
    },
    {
      "collectionGroup": "timesheet",
      "queryScope": "COLLECTION",
      "fields": [
        {
          "fieldPath": "uid",
          "order": "ASCENDING"
        },
        {
          "fieldPath": "timestamp",
          "order": "ASCENDING"
        }
      ]
    }
  ],
  "fieldOverrides": []
}
